soda/atlan/atlan_plugin.py
soda_core_atlan-3.5.6.dist-info/METADATA
soda_core_atlan-3.5.6.dist-info/WHEEL
soda_core_atlan-3.5.6.dist-info/top_level.txt
soda_core_atlan-3.5.6.dist-info/RECORD
