Metadata-Version: 2.1
Name: soda-core-atlan
Version: 3.5.6
Requires-Dist: soda-core==3.5.6
Requires-Dist: pyatlan<3.0,>=2.2.4
